{
  "version": "7",
  "dialect": "sqlite",
  "id": "8ce3c303-2bc9-44fd-8b95-d4388df13fff",
  "prevIds": [
    "00000000-0000-0000-0000-000000000000"
  ],
  "ddl": [
    {
      "name": "tasks",
      "entityType": "tables"
    },
    {
      "type": "text",
      "notNull": false,
      "autoincrement": false,
      "default": null,
      "generated": null,
      "name": "id",
      "entityType": "columns",
      "table": "tasks"
    },
    {
      "type": "text",
      "notNull": true,
      "autoincrement": false,
      "default": null,
      "generated": null,
      "name": "name",
      "entityType": "columns",
      "table": "tasks"
    },
    {
      "type": "text",
      "notNull": true,
      "autoincrement": false,
      "default": "'planned'",
      "generated": null,
      "name": "status",
      "entityType": "columns",
      "table": "tasks"
    },
    {
      "type": "integer",
      "notNull": true,
      "autoincrement": false,
      "default": "(unixepoch() * 1000)",
      "generated": null,
      "name": "created_at",
      "entityType": "columns",
      "table": "tasks"
    },
    {
      "type": "integer",
      "notNull": true,
      "autoincrement": false,
      "default": null,
      "generated": null,
      "name": "updated_at",
      "entityType": "columns",
      "table": "tasks"
    },
    {
      "columns": [
        "id"
      ],
      "nameExplicit": false,
      "name": "tasks_pk",
      "table": "tasks",
      "entityType": "pks"
    }
  ],
  "renames": []
}